{
    "id": 3713,
    "full_name": "Homalium guillainii",
    "authors": "(Vieill.) Briq.",
    "rank_name": "species",
    "metadata": {
        "rank_name": "species",
        "id_endemia": 870
    },
    "lft": 3047,
    "rght": 3048,
    "level": 2,
    "parent_id": 870,
    "taxon_id": 3713,
    "total_occurrences_count": 202,
    "occurrences_locations_coordinates": "{\"type\": \"MultiPoint\", \"coordinates\": [{\"coordinates\": [166.91, -22.2986111], \"count\": 2}, {\"coordinates\": [166.507081, -22.2299985], \"count\": 1}, {\"coordinates\": [166.9972287, -22.2614004], \"count\": 1}, {\"coordinates\": [165.9974767, -21.50644], \"count\": 1}, {\"coordinates\": [166.6958044, -22.1642337], \"count\": 2}, {\"coordinates\": [166.8267182, -22.2983825], \"count\": 1}, {\"coordinates\": [166.4331973, -22.166286], \"count\": 1}, {\"coordinates\": [166.9419199, -22.346665], \"count\": 2}, {\"coordinates\": [166.9163289, -22.3224198], \"count\": 1}, {\"coordinates\": [166.91511398, -22.30698298], \"count\": 2}, {\"coordinates\": [166.89416669, -22.28333333], \"count\": 4}, {\"coordinates\": [166.688626, -22.15952901], \"count\": 1}, {\"coordinates\": [166.91365673, -22.32333604], \"count\": 1}, {\"coordinates\": [166.91944437, -22.32472222], \"count\": 59}, {\"coordinates\": [166.91024923, -22.32176707], \"count\": 1}, {\"coordinates\": [166.62572499, -22.19208599], \"count\": 6}, {\"coordinates\": [166.64717056, -22.11350496], \"count\": 2}, {\"coordinates\": [166.85342804, -22.074305], \"count\": 3}, {\"coordinates\": [166.76361107, -22.17805556], \"count\": 1}, {\"coordinates\": [166.91232509, -22.32773786], \"count\": 1}, {\"coordinates\": [166.897293, -22.279661], \"count\": 1}, {\"coordinates\": [166.907922, -22.282192], \"count\": 1}, {\"coordinates\": [166.899976, -22.30008], \"count\": 3}, {\"coordinates\": [166.90829, -22.282251], \"count\": 1}, {\"coordinates\": [166.90391944444445, -22.274947222222224], \"count\": 8}, {\"coordinates\": [166.91754722222223, -22.32334722222222], \"count\": 1}, {\"coordinates\": [166.91658611111112, -22.31903888888889], \"count\": 3}, {\"coordinates\": [166.91542777777778, -22.32228611111111], \"count\": 1}, {\"coordinates\": [166.91771666666668, -22.319005555555556], \"count\": 8}, {\"coordinates\": [166.91701666666665, -22.322566666666667], \"count\": 3}, {\"coordinates\": [166.9188861111111, -22.32347222222222], \"count\": 10}, {\"coordinates\": [166.91840833333333, -22.324419444444445], \"count\": 4}, {\"coordinates\": [166.91736666666668, -22.321202777777778], \"count\": 2}, {\"coordinates\": [166.91972777777778, -22.319808333333334], \"count\": 2}, {\"coordinates\": [166.91715, -22.32363611111111], \"count\": 4}, {\"coordinates\": [166.9180861111111, -22.3246], \"count\": 1}, {\"coordinates\": [166.626125, -22.195666666666668], \"count\": 2}, {\"coordinates\": [166.9191, -22.321136111111112], \"count\": 1}, {\"coordinates\": [166.9187, -22.323591666666665], \"count\": 2}, {\"coordinates\": [166.91786944444445, -22.318091666666668], \"count\": 1}, {\"coordinates\": [166.91660277777777, -22.32164722222222], \"count\": 9}, {\"coordinates\": [166.9134388888889, -22.318802777777776], \"count\": 2}, {\"coordinates\": [166.91471944444444, -22.324102777777778], \"count\": 1}, {\"coordinates\": [166.6232, -22.1944], \"count\": 2}, {\"coordinates\": [166.91424722222223, -22.32207777777778], \"count\": 3}, {\"coordinates\": [165.93333435058594, -21.5], \"count\": 1}, {\"coordinates\": [166.89999996, -22.1666667], \"count\": 1}, {\"coordinates\": [166.9088897705078, -22.3075008392334], \"count\": 2}, {\"coordinates\": [166.9225647, -22.3216887], \"count\": 1}, {\"coordinates\": [166.9166717529297, -22.333332061767578], \"count\": 1}, {\"coordinates\": [166.45404052734375, -22.266090393066406], \"count\": 2}, {\"coordinates\": [166.818115234375, -22.32430076599121], \"count\": 3}, {\"coordinates\": [163.6602783203125, -19.721389770507812], \"count\": 2}, {\"coordinates\": [166.4166717529297, -21.833332061767578], \"count\": 1}, {\"coordinates\": [166.96665954589844, -22.333332061767578], \"count\": 1}, {\"coordinates\": [166.8973584, -22.2802817], \"count\": 1}, {\"coordinates\": [166.8236083984375, -22.301389694213867], \"count\": 4}, {\"coordinates\": [166.8412307, -22.2229916], \"count\": 2}, {\"coordinates\": [165.5758056640625, -21.5049991607666], \"count\": 1}, {\"coordinates\": [166.68443298339844, -22.11277961730957], \"count\": 1}, {\"coordinates\": [165.83435299999996, -21.46572900064235], \"count\": 1}, {\"coordinates\": [166.92083740234375, -22.337779998779297], \"count\": 1}, {\"coordinates\": [166.9242017, -22.3348215], \"count\": 1}, {\"coordinates\": [166.67612005, -22.04756799], \"count\": 1}, {\"coordinates\": [166.9063444, -22.29200828], \"count\": 1}, {\"coordinates\": [166.67986298, -22.04441702], \"count\": 1}, {\"coordinates\": [166.90349952, -22.27474405], \"count\": 1}]}",
    "species_top": {
        "Homalium guillainii": 202
    },
    "um_occurrences_true": 196,
    "um_occurrences_false": 6,
    "phenology_temporal_phenology": {
        "data": {
            "flowering": [
                66.67,
                100.0,
                100.0,
                71.43,
                22.22,
                66.67,
                0.0,
                0.0,
                0,
                0,
                0,
                0
            ],
            "fruiting": [
                0.0,
                0.0,
                0.0,
                0.0,
                0.0,
                0.0,
                0.0,
                0.0,
                0,
                0,
                0,
                0
            ]
        },
        "labels": [
            "Jan",
            "Feb",
            "Mar",
            "Apr",
            "May",
            "Jun",
            "Jul",
            "Aug",
            "Sep",
            "Oct",
            "Nov",
            "Dec"
        ]
    },
    "dbh_mean": 12.83,
    "dbh_max": 35.3,
    "dbh_median": 11.6,
    "dbh_min": 5.6,
    "height_max": 12.0,
    "wood_density_mean": 0.83,
    "wood_density_max": 0.86,
    "wood_density_min": 0.81,
    "bark_thickness_mean": null,
    "bark_thickness_max": null,
    "bark_thickness_min": null,
    "leaf_sla_mean": null,
    "leaf_sla_max": null,
    "leaf_sla_min": null,
    "leaf_area_mean": null,
    "leaf_area_max": null,
    "leaf_area_min": null,
    "leaf_thickness_mean": null,
    "leaf_thickness_max": null,
    "leaf_thickness_min": null,
    "frequencies": {
        "dbh": {
            "10": 81.44,
            "20": 15.46,
            "30": 3.09,
            "40": 0.0,
            "50": 0.0,
            "75": 0.0,
            "100": 0.0,
            "200": 0.0,
            "300": 0.0,
            "400": 0.0
        },
        "elevation": {
            "100": 8.84,
            "200": 74.03,
            "300": 14.92,
            "400": 1.66,
            "500": 0.0,
            "600": 0.0,
            "700": 0.0,
            "800": 0.0,
            "900": 0.55,
            "1000": 0.0,
            "1100": 0.0,
            "1200": 0.0
        },
        "rainfall": {
            "1000": 3.03,
            "1500": 0.51,
            "2000": 6.06,
            "2500": 82.83,
            "3000": 7.58,
            "3500": 0.0,
            "4000": 0.0,
            "4500": 0.0
        },
        "holdridge": {
            "1": 17.86,
            "2": 82.14
        },
        "strate": {
            "1": 12.5,
            "2": 62.5,
            "3": 25.0
        }
    }
}